setup.py
knightswhosay/__init__.py
knightswhosay/knights.py
knightswhosay.egg-info/PKG-INFO
knightswhosay.egg-info/SOURCES.txt
knightswhosay.egg-info/dependency_links.txt
knightswhosay.egg-info/not-zip-safe
knightswhosay.egg-info/requires.txt
knightswhosay.egg-info/top_level.txt