Metadata-Version: 1.0
Name: knightswhosay
Version: 0.1
Summary: Knights who say stugg
Home-page: UNKNOWN
Author: Flying Circus
Author-email: flyingcircus@example.com
License: BoNoBo
Platform: UNKNOWN
